Workbook

Sheet Cover
B2: GBENGA QUADRI
B3: CFA Candidate | Credit Analysis & Leveraged Finance
B5: KESKO CORPORATION
B6: Credit Analysis & Debt Capacity Model
B7: OMX Helsinki: KESKOB | Implied Rating: BBB+ / Baa1
B9: CREDIT ASSESSMENT: INVESTMENT GRADE — STRONG
B10: Maximum incremental debt capacity: EUR 1,300-1,800M before downgrade risk
B12: Key Credit Metrics (FY2025):
B13: Net Debt / EBITDA (excl. leases): 0.8x — well within IG thresholds
B14: Total Debt / EBITDA (incl. IFRS 16): 3.1x — typical for lease-heavy retail
B15: Interest Coverage (EBITDA / Interest): 9.9x — strong
B16: Free Cash Flow: EUR 350M+ — ample debt service capacity
... B35: March 2026

Sheet EBITDA_Analysis
A1: EBITDA ANALYSIS — HISTORICAL & PROJECTED
A2: GBENGA QUADRI CFA CANDIDATE | E2: All figures in EUR M
B4: Unit | C4: 2023A | D4: 2024A | E4: 2025A | F4: 2026E | G4: 2027E | H4: 2028E
A5: REVENUE BUILD
A6: Grocery Trade | B6: EUR M | C6: 6106 | D6: 6245 | E6: 6669 | F6: 6869 | G6: 7075 | H6: 7287
A7: Building & Technical Trade | B7: EUR M | C7: 4509 | D7: 4147 | E7: 4462 | F7: 4596 | G7: 4781 | H7: 4972
A8: Car Trade | B8: EUR M | C8: 1338 | D8: 1287 | E8: 1366 | F8: 1407 | G8: 1449 | H8: 1493
A9: Eliminations | B9: EUR M | C9: -75 | D9: -68 | E9: -72 | F9: -73 | G9: -75 | H9: -77
A10: Total Net Sales | B10: EUR M | C10: =SUM(C6:C9) -> 11878 | D10: =SUM(D6:D9) -> 11611 | E10: =SUM(E6:E9) -> 12425 | F10: =SUM(F6:F9) -> 12799 | G10: =SUM(G6:G9) -> 13230 | H10: =SUM(H6:H9) -> 13675
A11: Revenue Growth | B11: % | D11: =D10/C10-1 -> -0.022478532 | E11: =E10/D10-1 -> 0.070105934 | F11: =F10/E10-1 -> 0.030100604 | G11: =G10/F10-1 -> 0.033674506 | H11: =H10/G10-1 -> 0.033635676
A13: EBITDA BUILD
A14: Gross Profit | B14: EUR M | C14: 1650 | D14: 1720 | E14: 1795 | F14: 1868 | G14: 1952 | H14: 2040
A15: Gross Margin | B15: % | C15: =C14/C10 -> 0.13891227 | D15: =D14/D10 -> 0.14813539 | E15: =E14/E10 -> 0.1444668 | F15: =F14/F10 -> 0.1459489 | G15: =G14/G10 -> 0.14754346 | H15: =H14/H10 -> 0.14917733
A16: SG&A + Other OpEx | B16: EUR M | C16: -580 | D16: -600 | E16: -640 | F16: -655 | G16: -670 | H16: -685
A17: Other Operating Items | B17: EUR M | C17: -20 | D17: -15 | E17: -20 | F17: -15 | G17: -15 | H17: -15
A18: EBITDA (incl. IFRS 16) | B18: EUR M | C18: 1050 | D18: 1105 | E18: 1135 | F18: 1198 | G18: 1267 | H18: 1340
A19: EBITDA Margin | B19: % | C19: =C18/C10 -> 0.08839872 | D19: =D18/D10 -> 0.095168375 | E19: =E18/E10 -> 0.091348089 | F19: =F18/F10 -> 0.093601063 | G19: =G18/G10 -> 0.095767196 | H19: =H18/H10 -> 0.097989031
A20: EBITDA Growth | B20: % | D20: =D18/C18-1 -> 0.052380952 | E20: =E18/D18-1 -> 0.027149321 | F20: =F18/E18-1 -> 0.055506608 | G20: =G18/F18-1 -> 0.057595993 | H20: =H18/G18-1 -> 0.057616417
A22: D&A (incl. IFRS 16) | B22: EUR M | C22: -430 | D22: -455 | E22: -480 | F22: -490 | G22: -500 | H22: -510
A23: Comparable Operating Profit | C23: =C18+C22 -> 620 | D23: =D18+D22 -> 650 | E23: =E18+E22 -> 655 | F23: =F18+F22 -> 708 | G23: =G18+G22 -> 767 | H23: =H18+H22 -> 830
A25: Net Finance Costs | C25: -105 | D25: -110 | E25: -115 | F25: -110 | G25: -105 | H25: -100
A26: CapEx | C26: -380 | D26: -420 | E26: -450 | F26: -470 | G26: -460 | H26: -450
A27: Change in NWC | C27: -15 | D27: -20 | E27: -25 | F27: -20 | G27: -18 | H27: -15
A28: Tax Paid | C28: =-C23*0.2 -> -124 | D28: =-D23*0.2 -> -130 | E28: =-E23*0.2 -> -131 | F28: =-F23*0.2 -> -141.6 | G28: =-G23*0.2 -> -153.4 | H28: =-H23*0.2 -> -166
A29: Free Cash Flow | C29: =C18+C26+C27+C28 -> 531 | D29: =D18+D26+D27+D28 -> 535 | E29: =E18+E26+E27+E28 -> 529 | F29: =F18+F26+F27+F28 -> 566.4 | G29: =G18+G26+G27+G28 -> 635.6 | H29: =H18+H26+H27+H28 -> 709
A31: Model follows CFI Financial Modeling Best Practices & Financial Modeling Guidelines
A32: GBENGA QUADRI CFA CANDIDATE | March 2026

Sheet Leverage_Ratios
A1: LEVERAGE RATIO ANALYSIS
A2: GBENGA QUADRI CFA CANDIDATE
B4: Unit | C4: 2023A | D4: 2024A | E4: 2025A | F4: 2026E | G4: 2027E | H4: 2028E | I4: Threshold
A5: DEBT BALANCES
A6: Financial Debt (excl. leases) | B6: EUR M | C6: 1380 | D6: 1360 | E6: 1345 | F6: 1295 | G6: 1195 | H6: 1095
A7: Bonds | B7: EUR M | C7: 800 | D7: 800 | E7: 800 | F7: 800 | G7: 650 | H7: 650
A8: Bank Term Loans | B8: EUR M | C8: 500 | D8: 480 | E8: 465 | F8: 415 | G8: 465 | H8: 365
A9: Other Financial Debt | B9: EUR M | C9: 80 | D9: 80 | E9: 80 | F9: 80 | G9: 80 | H9: 80
A10: IFRS 16 Lease Liabilities | B10: EUR M | C10: 2100 | D10: 2130 | E10: 2151 | F10: 2180 | G10: 2200 | H10: 2220
A11: Total Debt (incl. leases) | B11: EUR M | C11: =C6+C10 -> 3480 | D11: =D6+D10 -> 3490 | E11: =E6+E10 -> 3496 | F11: =F6+F10 -> 3475 | G11: =G6+G10 -> 3395 | H11: =H6+H10 -> 3315
A12: Cash & Equivalents | B12: EUR M | C12: 520 | D12: 505 | E12: 488 | F12: 510 | G12: 545 | H12: 590
A13: Net Debt (excl. leases) | B13: EUR M | C13: =C6-C12 -> 860 | D13: =D6-D12 -> 855 | E13: =E6-E12 -> 857 | F13: =F6-F12 -> 785 | G13: =G6-G12 -> 650 | H13: =H6-H12 -> 505
A14: Net Debt (incl. leases) | B14: EUR M | C14: =C11-C12 -> 2960 | D14: =D11-D12 -> 2985 | E14: =E11-E12 -> 3008 | F14: =F11-F12 -> 2965 | G14: =G11-G12 -> 2850 | H14: =H11-H12 -> 2725
A16: KEY LEVERAGE RATIOS
A17: EBITDA | B17: EUR M | C17: =EBITDA_Analysis!C18 -> 1050 | D17: =EBITDA_Analysis!D18 -> 1105 | E17: =EBITDA_Analysis!E18 -> 1135 | F17: =EBITDA_Analysis!F18 -> 1198 | G17: =EBITDA_Analysis!G18 -> 1267 | H17: =EBITDA_Analysis!H18 -> 1340
A18: Net Debt / EBITDA (excl. leases) | B18: x | C18: =C13/C17 -> 0.81904762 | D18: =D13/D17 -> 0.77375566 | E18: =E13/E17 -> 0.75506608 | F18: =F13/F17 -> 0.65525876 | G18: =G13/G17 -> 0.51302289 | H18: =H13/H17 -> 0.37686567 | I18: < 2.5x (IG)
A19: Total Debt / EBITDA (incl. leases) | C19: =C11/C17 -> 3.3142857 | D19: =D11/D17 -> 3.158371 | E19: =E11/E17 -> 3.0801762 | F19: =F11/F17 -> 2.9006678 | G19: =G11/G17 -> 2.679558 | H19: =H11/H17 -> 2.4738806 | I19: < 4.0x (IG retail)
A20: Net Debt / EBITDA (incl. leases) | C20: =C14/C17 -> 2.8190476 | D20: =D14/D17 -> 2.7013575 | E20: =E14/E17 -> 2.6502203 | F20: =F14/F17 -> 2.4749583 | G20: =G14/G17 -> 2.2494081 | H20: =H14/H17 -> 2.0335821 | I20: < 3.5x (IG retail)
A21: Gross Debt / EBITDA | C21: =C6/C17 -> 1.3142857 | D21: =D6/D17 -> 1.2307692 | E21: =E6/E17 -> 1.185022 | F21: =F6/F17 -> 1.0809683 | G21: =G6/G17 -> 0.94317285 | H21: =H6/H17 -> 0.81716418
A23: INDUSTRY LEVERAGE BENCHMARKS
A24: Kesko (current) | C24: 0.8x | E24: 3.1x | G24: BBB+ / Baa1 implied
A25: Ahold Delhaize | C25: 1.7x | E25: 2.8x | G25: BBB / Baa1
A26: Tesco PLC | C26: 2.4x | E26: 3.5x | G26: BBB- / Baa3
A27: Carrefour SA | C27: 2.3x | E27: 3.8x | G27: BBB / Baa1
A28: Axfood AB | C28: 0.8x | E28: 2.2x | G28: Not rated (implied A-)
A29: European Grocery Median | C29: 1.8x | E29: 3.2x | G29: BBB / Baa2
A31: Model follows CFI Financial Modeling Best Practices & Financial Modeling Guidelines
A32: GBENGA QUADRI CFA CANDIDATE | March 2026

Sheet Interest_Coverage
A1: INTEREST COVERAGE ANALYSIS
A2: GBENGA QUADRI CFA CANDIDATE
B4: Unit | C4: 2023A | D4: 2024A | E4: 2025A | F4: 2026E | G4: 2027E | H4: 2028E | I4: Min. Threshold
A5: EBITDA | B5: EUR M | C5: =EBITDA_Analysis!C18 -> 1050 | D5: =EBITDA_Analysis!D18 -> 1105 | E5: =EBITDA_Analysis!E18 -> 1135 | F5: =EBITDA_Analysis!F18 -> 1198 | G5: =EBITDA_Analysis!G18 -> 1267 | H5: =EBITDA_Analysis!H18 -> 1340
A6: EBIT | C6: =EBITDA_Analysis!C23 -> 620 | D6: =EBITDA_Analysis!D23 -> 650 | E6: =EBITDA_Analysis!E23 -> 655 | F6: =EBITDA_Analysis!F23 -> 708 | G6: =EBITDA_Analysis!G23 -> 767 | H6: =EBITDA_Analysis!H23 -> 830
A7: Net Interest Expense | C7: =EBITDA_Analysis!C25 -> -105 | D7: =EBITDA_Analysis!D25 -> -110 | E7: =EBITDA_Analysis!E25 -> -115 | F7: =EBITDA_Analysis!F25 -> -110 | G7: =EBITDA_Analysis!G25 -> -105 | H7: =EBITDA_Analysis!H25 -> -100
A8: of which: Lease Interest (est.) | C8: -55 | D8: -57 | E8: -60 | F8: -62 | G8: -63 | H8: -64
A9: of which: Financial Debt Interest | C9: =C7-C8 -> -50 | D9: =D7-D8 -> -53 | E9: =E7-E8 -> -55 | F9: =F7-F8 -> -48 | G9: =G7-G8 -> -42 | H9: =H7-H8 -> -36
A11: COVERAGE RATIOS
A12: EBITDA / Total Interest | C12: =C5/(-C7) -> 10 | D12: =D5/(-D7) -> 10.045455 | E12: =E5/(-E7) -> 9.8695652 | F12: =F5/(-F7) -> 10.890909 | G12: =G5/(-G7) -> 12.066667 | H12: =H5/(-H7) -> 13.4 | I12: > 4.0x (IG min)
A13: EBITDA / Financial Interest Only | C13: =C5/(-C9) -> 21 | D13: =D5/(-D9) -> 20.849057 | E13: =E5/(-E9) -> 20.636364 | F13: =F5/(-F9) -> 24.958333 | G13: =G5/(-G9) -> 30.166667 | H13: =H5/(-H9) -> 37.222222 | I13: > 6.0x (strong IG)
A14: EBIT / Total Interest | C14: =C6/(-C7) -> 5.9047619 | D14: =D6/(-D7) -> 5.9090909 | E14: =E6/(-E7) -> 5.6956522 | F14: =F6/(-F7) -> 6.4363636 | G14: =G6/(-G7) -> 7.3047619 | H14: =H6/(-H7) -> 8.3 | I14: > 2.5x (IG min)
A15: Free Cash Flow | C15: =EBITDA_Analysis!C29 -> 531 | D15: =EBITDA_Analysis!D29 -> 535 | E15: =EBITDA_Analysis!E29 -> 529 | F15: =EBITDA_Analysis!F29 -> 566.4 | G15: =EBITDA_Analysis!G29 -> 635.6 | H15: =EBITDA_Analysis!H29 -> 709
A16: FCF / Total Interest | C16: =C15/(-C7) -> 5.0571429 | D16: =D15/(-D7) -> 4.8636364 | E16: =E15/(-E7) -> 4.6 | F16: =F15/(-F7) -> 5.1490909 | G16: =G15/(-G7) -> 6.0533333 | H16: =H15/(-H7) -> 7.09 | I16: > 2.0x (adequate)
A17: FCF / Total Debt Service | C17: =IF((-C7+C18)=0,0,C15/(-C7+C18)) -> 5.0571429 | D17: =IF((-D7+D18)=0,0,D15/(-D7+D18)) -> 4.8636364 | E17: =IF((-E7+E18)=0,0,E15/(-E7+E18)) -> 1.9962264 | F17: =IF((-F7+F18)=0,0,F15/(-F7+F18)) -> 2.1784615 | G17: =IF((-G7+G18)=0,0,G15/(-G7+G18)) -> 1.3969231 | H17: =IF((-H7+H18)=0,0,H15/(-H7+H18)) -> 3.545 | I17: > 1.0x (min)
A18: Scheduled Repayments | C18: 0 | D18: 0 | E18: 150 | F18: 150 | G18: 350 | H18: 100
A20: COVERAGE ASSESSMENT
A21: EBITDA / Interest: WELL ABOVE IG minimum at 9-13x
A22: EBIT / Interest: ABOVE IG minimum at 5-7x
A23: FCF / Total Debt Service: Watch 2027E — EUR 350M maturity wall
A24: Conclusion: Strong coverage across all metrics; 2027 maturity needs refinancing plan
A26: Model follows CFI Financial Modeling Best Practices & Financial Modeling Guidelines
A27: GBENGA QUADRI CFA CANDIDATE | March 2026

Sheet Debt_Structure
A1: DEBT STRUCTURE & MATURITY PROFILE
A2: GBENGA QUADRI CFA CANDIDATE
A4: Instrument | B4: Unit | C4: Amount (EUR M) | D4: Coupon / Rate | E4: Maturity | F4: Security | G4: Notes
A5: SENIOR SECURED
A6: NIB Sustainability-Linked Loan | B6: EUR M | C6: 150 | D6: 3.25% | E6: 2031 | F6: Secured | G6: EUR 150M 7yr; margin tied to ESG targets
A7: Revolving Credit Facility (undrawn) | B7: EUR M | C7: 0 | D7: Euribor+85bps | E7: 2028 | F7: Secured | G7: EUR 400M committed; fully undrawn
A8: SENIOR UNSECURED
A9: Green Notes (Sep 2024) | B9: EUR M | C9: 300 | D9: 3.50% | E9: Feb 2030 | F9: Unsecured | G9: EUR 300M; annual coupon; green bond framework
A10: Term Loan Facility A | B10: EUR M | C10: 150 | D10: Euribor+110bps | E10: 2026 | F10: Unsecured | G10: Maturing 2026; refinancing needed
A11: Term Loan Facility B | B11: EUR M | C11: 150 | D11: Euribor+120bps | E11: 2027 | F11: Unsecured | G11: Part of EUR 350M 2027 maturity wall
A12: Term Loan Facility C | B12: EUR M | C12: 200 | D12: Euribor+130bps | E12: 2027 | F12: Unsecured | G12: Part of EUR 350M 2027 maturity wall
A13: Bond (legacy) | B13: EUR M | C13: 300 | D13: 2.875% | E13: 2026 | F13: Unsecured | G13: Maturing 2026; refinancing at higher rate expected
A14: Other Bank Debt | B14: EUR M | C14: 95 | D14: Various | E14: Various | F14: Unsecured | G14: Bilateral facilities; Finnish banks
A15: SUBORDINATED / HYBRID
A16: None | B16: EUR M | C16: 0 | D16: N/A | E16: N/A | F16: N/A | G16: No subordinated or hybrid instruments
A17: LEASE LIABILITIES (IFRS 16)
A18: Right-of-Use Lease Obligations | B18: EUR M | C18: 2151 | D18: Implicit ~3.0% | E18: Various | F18: Operating | G18: Store leases, warehouses, offices; avg ~8yr tenor
A20: DEBT SUMMARY
A21: Total Financial Debt | C21: 1345
A22: Total Lease Liabilities | C22: 2151
A23: Total Debt (Financial + Leases) | C23: =C21+C22 -> 3496
A24: Undrawn RCF Capacity | C24: 400
A25: Total Available Liquidity | C25: =C24+488 -> 888
A27: MATURITY WALL
A28: 2026 | C28: 450
A29: 2027 | C29: 350
A30: 2028 | C30: 0
A31: 2029 | C31: 0
A32: 2030 | C32: 300
A33: 2031+ | C33: 245
A34: WARNING: EUR 450M matures in 2026, EUR 350M in 2027
A35: Recommendation: Initiate refinancing of 2026 maturities immediately
A37: Model follows CFI Financial Modeling Best Practices & Financial Modeling Guidelines
A38: GBENGA QUADRI CFA CANDIDATE | March 2026

Sheet Covenants
A1: FINANCIAL COVENANT ANALYSIS
A2: GBENGA QUADRI CFA CANDIDATE
A4: Covenant Test | B4: Unit | C4: Covenant Limit | D4: 2025A Actual | E4: 2026E Projected | F4: 2027E Projected | G4: Headroom (2025A)
A5: Net Debt / EBITDA (excl. leases) | B5: x | C5: 3.5 | D5: =Leverage_Ratios!E18 -> 0.75506608 | E5: =Leverage_Ratios!F18 -> 0.65525876 | F5: =Leverage_Ratios!G18 -> 0.51302289 | G5: =C5-D5 -> 2.7449339
A6: Total Debt / EBITDA (incl. leases) | B6: x | C6: 5 | D6: =Leverage_Ratios!E19 -> 3.0801762 | E6: =Leverage_Ratios!F19 -> 2.9006678 | F6: =Leverage_Ratios!G19 -> 2.679558 | G6: =C6-D6 -> 1.9198238
A7: Interest Coverage (EBITDA/Int) | B7: x | C7: 3 | D7: =Interest_Coverage!E12 -> 9.8695652 | E7: =Interest_Coverage!F12 -> 10.890909 | F7: =Interest_Coverage!G12 -> 12.066667 | G7: =D7-C7 -> 6.8695652
A8: Minimum EBITDA | B8: EUR M | C8: 800 | D8: =EBITDA_Analysis!E18 -> 1135 | E8: =EBITDA_Analysis!F18 -> 1198 | F8: =EBITDA_Analysis!G18 -> 1267 | G8: =D8-C8 -> 335
A9: Maximum CapEx | B9: EUR M | C9: 600 | D9: =-EBITDA_Analysis!E26 -> 450 | E9: =-EBITDA_Analysis!F26 -> 470 | F9: =-EBITDA_Analysis!G26 -> 460 | G9: =C9-D9 -> 150
A10: Dividend Restriction | B10: % | C10: 0.75 | D10: 0.55 | E10: 0.52 | F10: 0.5 | G10: =C10-D10 -> 0.2
A12: COMPLIANCE STATUS
A13: Net Debt / EBITDA (excl. leases) | D13: =IF(D5<=C5,"PASS","BREACH") -> PASS
A14: Total Debt / EBITDA (incl. leases) | D14: =IF(D6<=C6,"PASS","BREACH") -> PASS
A15: Interest Coverage (EBITDA/Int) | D15: =IF(D7>=C7,"PASS","BREACH") -> PASS
A16: Minimum EBITDA | D16: =IF(D8>=C8,"PASS","BREACH") -> PASS
A17: Maximum CapEx | D17: =IF(D9<=C9,"PASS","BREACH") -> PASS
A18: Dividend Restriction | D18: =IF(D10<=C10,"PASS","BREACH") -> PASS
A20: All covenants comfortably met. Significant headroom on all tests.
A21: ND/EBITDA headroom of ~2.7x means Kesko could take on substantial additional debt
A22: before approaching covenant limits.
A24: Model follows CFI Financial Modeling Best Practices & Financial Modeling Guidelines
A25: GBENGA QUADRI CFA CANDIDATE | March 2026

Sheet Maximum_Debt
A1: MAXIMUM DEBT CAPACITY ANALYSIS
A2: GBENGA QUADRI CFA CANDIDATE
B4: Unit | C4: Conservative (Maintain A-) | D4: Base Case (Maintain BBB) | E4: Aggressive (BBB- Floor)
A5: TARGET LEVERAGE
A6: Target ND/EBITDA (excl. leases) | C6: 1.5 | D6: 2 | E6: 2.5
A7: FY2025 EBITDA | C7: 1135 | D7: 1135 | E7: 1135
A8: Maximum Net Debt (excl. leases) | C8: =C6*C7 -> 1702.5 | D8: =D6*D7 -> 2270 | E8: =E6*E7 -> 2837.5
A9: Current Net Debt (excl. leases) | C9: 857 | D9: 857 | E9: 857
A10: INCREMENTAL DEBT CAPACITY | C10: =C8-C9 -> 845.5 | D10: =D8-D9 -> 1413 | E10: =E8-E9 -> 1980.5
A12: SENSITIVITY: DEBT CAPACITY BY EBITDA LEVEL
A13: EBITDA (EUR M) | C13: At 1.5x | D13: At 2.0x | E13: At 2.5x
A14: 1000 | C14: 643 | D14: 1143 | E14: 1643
A15: 1050 | C15: 718 | D15: 1243 | E15: 1768
A16: 1100 | C16: 793 | D16: 1343 | E16: 1893
A17: 1135 | C17: 845.5 | D17: 1413 | E17: 1980.5
A18: 1200 | C18: 943 | D18: 1543 | E18: 2143
A19: 1300 | C19: 1093 | D19: 1743 | E19: 2393
A21: POTENTIAL USES OF INCREMENTAL CAPACITY (BASE CASE: EUR ~1,400M)
A22: M&A (e.g., Tokmanni at 70% cash) | C22: 720 | E22: Per M&A model; EUR 662M equity + fees
A23: Accelerated CapEx (logistics) | C23: 200 | E23: Hyvinkaa-scale investment
A24: Share Buyback Programme | C24: 300 | E24: Opportunistic repurchases
A25: Refinancing Buffer | C25: 200 | E25: Pre-fund 2026/2027 maturities
A27: Model follows CFI Financial Modeling Best Practices & Financial Modeling Guidelines
A28: GBENGA QUADRI CFA CANDIDATE | March 2026

Sheet Pricing_Grid
A1: DEBT PRICING GRID
A2: GBENGA QUADRI CFA CANDIDATE
A4: INDICATIVE SPREAD GRID (bps over Euribor / Mid-Swap)
A5: ND/EBITDA | B5: Senior Secured 5yr | C5: Senior Unsecured 5yr | D5: Senior Unsecured 7yr | E5: Senior Unsecured 10yr | F5: Implied Rating
A6: 0.5 | B6: 55 | C6: 80 | D6: 95 | E6: 115 | F6: A / A2
A7: 1 | B7: 65 | C7: 95 | D7: 110 | E7: 130 | F7: A- / A3
A8: 1.5 | B8: 80 | C8: 115 | D8: 135 | E8: 155 | F8: BBB+ / Baa1
A9: 2 | B9: 100 | C9: 140 | D9: 165 | E9: 190 | F9: BBB / Baa2
A10: 2.5 | B10: 130 | C10: 175 | D10: 205 | E10: 240 | F10: BBB- / Baa3
A11: 3 | B11: 175 | C11: 235 | D11: 275 | E11: 320 | F11: BB+ / Ba1
A12: 3.5 | B12: 240 | C12: 320 | D12: 380 | E12: 440 | F12: BB / Ba2
A13: 4 | B13: 325 | C13: 430 | D13: 500 | E13: 575 | F13: BB- / Ba3
A15: KESKO CURRENT COST OF DEBT
A16: Current ND/EBITDA | B16: 0.8
A17: Weighted Avg Cost | B17: 0.035
A18: After-Tax Cost | B18: =B17*(1-0.2) -> 0.028
A19: Tax Rate | B19: 0.2
A21: REFINANCING COST ESTIMATE (2026-2027 MATURITIES)
A22: Amount to Refinance | B22: 800
A23: Assumed Tenor | B23: 5-7 years
A24: Current Euribor (3M) | B24: 0.0265
A25: Estimated Spread | B25: 0.0095
A26: All-in Refinancing Rate | B26: =B24+B25 -> 0.036
A27: Annual Interest Cost | B27: =B22*B26 -> 28.8
A28: vs. Maturing Debt Avg Rate | B28: 0.028
A29: Incremental Annual Cost | B29: =B22*(B26-B28) -> 6.4
A31: Model follows CFI Financial Modeling Best Practices & Financial Modeling Guidelines
A32: GBENGA QUADRI CFA CANDIDATE | March 2026
